deepehr/__init__.py
deepehr/layers.py
deepehr-0.1.1.dist-info/WHEEL
deepehr-0.1.1.dist-info/METADATA
deepehr-0.1.1.dist-info/RECORD
