Metadata-Version: 2.1
Name: deepehr
Version: 0.1.1
Summary: Deep Learning for EHR Analysis
Author: yajiez
Author-email: yajiez.me@gmail.com
Requires-Python: >=3.7,<4.0
Classifier: Programming Language :: Python :: 3
Classifier: Programming Language :: Python :: 3.7
Classifier: Programming Language :: Python :: 3.8
Requires-Dist: gensim (>=3.8.1,<4.0.0)
Requires-Dist: ipykernel (>=5.1.3,<6.0.0)
Requires-Dist: pandas (>=0.25.3,<0.26.0)
Requires-Dist: seaborn (>=0.9.0,<0.10.0)
Requires-Dist: torch (>=1.3.1,<2.0.0)
